{
  "act1": {
    "totalPills": 76000000000,
    "yearly": [
      { "year": 2006, "pills": 8400000000 },
      { "year": 2007, "pills": 8900000000 },
      { "year": 2008, "pills": 9200000000 },
      { "year": 2009, "pills": 9400000000 },
      { "year": 2010, "pills": 9600000000 },
      { "year": 2011, "pills": 9500000000 },
      { "year": 2012, "pills": 8900000000 },
      { "year": 2013, "pills": 7800000000 },
      { "year": 2014, "pills": 6900000000 }
    ]
  },
  "act2": {
    "rows": [
      { "distributor": "McKesson", "start": 38.2, "end": 34.1, "emphasized": true },
      { "distributor": "Cardinal", "start": 25.9, "end": 22.7, "emphasized": true },
      { "distributor": "AmerisourceBergen", "start": 16.0, "end": 19.4, "emphasized": true },
      { "distributor": "CVS", "start": 4.1, "end": 4.5, "emphasized": false },
      { "distributor": "Walgreens", "start": 3.6, "end": 4.2, "emphasized": false },
      { "distributor": "Walmart", "start": 2.5, "end": 2.9, "emphasized": false },
      { "distributor": "H.D. Smith", "start": 2.1, "end": 2.0, "emphasized": false },
      { "distributor": "Anda", "start": 1.4, "end": 1.5, "emphasized": false },
      { "distributor": "Miami-Luken", "start": 0.8, "end": 0.4, "emphasized": false },
      { "distributor": "Other", "start": 5.4, "end": 8.3, "emphasized": false }
    ]
  },
  "act3": {
    "actions": [
      { "year": 2007, "action_count": 18, "notable_actions": [{ "title": "Cardinal Health MOA", "url": "" }] },
      { "year": 2008, "action_count": 22, "notable_actions": [] },
      { "year": 2009, "action_count": 27, "notable_actions": [] },
      { "year": 2010, "action_count": 32, "notable_actions": [] },
      { "year": 2011, "action_count": 34, "notable_actions": [] },
      { "year": 2012, "action_count": 41, "notable_actions": [{ "title": "CVS Sanford FL", "url": "" }] },
      { "year": 2013, "action_count": 47, "notable_actions": [{ "title": "Walgreens $80M", "url": "" }] },
      { "year": 2014, "action_count": 45, "notable_actions": [] }
    ]
  },
  "act4": {
    "counties": [
      { "fips": "54059", "name": "Mingo", "state": "WV", "deaths": [5, 7, 9, 12, 16, 18, 22, 25, 28] },
      { "fips": "51720", "name": "Norton", "state": "VA", "deaths": [2, 3, 5, 7, 8, 9, 11, 13, 14] },
      { "fips": "54011", "name": "Cabell", "state": "WV", "deaths": [12, 18, 25, 34, 44, 52, 61, 68, 75] },
      { "fips": "54045", "name": "Logan", "state": "WV", "deaths": [7, 10, 14, 17, 21, 26, 29, 32, 36] },
      { "fips": "21071", "name": "Floyd", "state": "KY", "deaths": [6, 8, 11, 15, 19, 22, 26, 29, 33] },
      { "fips": "21195", "name": "Pike", "state": "KY", "deaths": [11, 14, 19, 23, 28, 33, 38, 44, 49] }
    ]
  }
}
